MGEmasker-0.1.13.dist-info/METADATA
MGEmasker-0.1.13.dist-info/RECORD
MGEmasker-0.1.13.dist-info/WHEEL
MGEmasker-0.1.13.dist-info/entry_points.txt
MGEmasker-0.1.13.dist-info/top_level.txt
mge_masker/__init__.py
mge_masker/mge_masker_functions.py
mge_masker/mge_patterns.txt
mge_masker/run_mge_masker.py
mge_masker/tests/__init__.py
mge_masker/tests/test_find_mges.py
mge_masker/tests/test_mask_mges.py
mge_masker/tests/data/test.gbk
mge_masker/tests/data/test.gff
mge_masker/tests/data/test_alignment.fas
mge_masker/tests/data/test_alignment.masked.fas
