Metadata-Version: 2.1
Name: MGEmasker
Version: 0.1.13
Summary: UNKNOWN
Home-page: UNKNOWN
Author: Anthony Underwood
Author-email: au3@sanger.ac.uk
License: MIT
Platform: UNKNOWN
Requires-Python: >=3
License-File: LICENSE
Requires-Dist: biopython (>=1.7.9)
Requires-Dist: rich
